fastxmltodict/__init__.py
fastxmltodict/core.py
fastxmltodict/core.pyd
fastxmltodict-4.0.0.dist-info/METADATA
fastxmltodict-4.0.0.dist-info/WHEEL
fastxmltodict-4.0.0.dist-info/top_level.txt
fastxmltodict-4.0.0.dist-info/RECORD
