Metadata-Version: 2.2
Name: fastxmltodict
Version: 4.0.0
Summary: Быстрый парсер XML в dict
Author: MichaelScofield
Classifier: Programming Language :: Python :: 3
Classifier: License :: OSI Approved :: MIT License
Classifier: Operating System :: OS Independent
Requires-Python: >=3.6
Dynamic: author
Dynamic: classifier
Dynamic: requires-python
Dynamic: summary
